Metadata-Version: 2.1
Name: hid_ups_exporter
Version: 0.5.3
Summary: Export HID UPS stats to Prometheus
Author-email: Desultory <dev@pyl.onl>
Classifier: Programming Language :: Python :: 3
Classifier: License :: OSI Approved :: GNU General Public License v2 (GPLv2)
Classifier: Operating System :: OS Independent
Requires-Python: >=3.11
License-File: LICENSE
Requires-Dist: hid_ups>=0.7.0
Requires-Dist: prometheus_exporter>=0.13.2
Requires-Dist: zenlib>=1.7.1
